{"box_data": [{"position": {"minX": 75.25, "minY": 115.625, "maxX": 363.75, "maxY": 373.5}, "class_id": 1, "box_caption": "chair 0.884", "scores": {"class_score": 0.88427734375}, "domain": "pixel"}, {"position": {"minX": 336.0, "minY": 47.0, "maxX": 570.5, "maxY": 406.5}, "class_id": 1, "box_caption": "chair 0.879", "scores": {"class_score": 0.87939453125}, "domain": "pixel"}, {"position": {"minX": 615.0, "minY": 542.0, "maxX": 659.0, "maxY": 658.0}, "class_id": 0, "box_caption": "bottle 0.607", "scores": {"class_score": 0.60693359375}, "domain": "pixel"}, {"position": {"minX": 316.5, "minY": -22.75, "maxX": 537.5, "maxY": 489.25}, "class_id": 1, "box_caption": "chair 0.030", "scores": {"class_score": 0.0304412841796875}, "domain": "pixel"}, {"position": {"minX": 334.75, "minY": 45.0, "maxX": 569.5, "maxY": 409.25}, "class_id": 0, "box_caption": "bottle 0.009", "scores": {"class_score": 0.0092620849609375}, "domain": "pixel"}, {"position": {"minX": 614.0, "minY": 540.5, "maxX": 658.0, "maxY": 660.5}, "class_id": 3, "box_caption": "tripod 0.008", "scores": {"class_score": 0.00833892822265625}, "domain": "pixel"}, {"position": {"minX": 614.0, "minY": 541.0, "maxX": 659.0, "maxY": 658.0}, "class_id": 1, "box_caption": "chair 0.007", "scores": {"class_score": 0.0067901611328125}, "domain": "pixel"}, {"position": {"minX": 614.0, "minY": 541.0, "maxX": 659.0, "maxY": 658.0}, "class_id": 2, "box_caption": "stool 0.006", "scores": {"class_score": 0.006015777587890625}, "domain": "pixel"}, {"position": {"minX": 75.0, "minY": 116.125, "maxX": 363.75, "maxY": 373.0}, "class_id": 0, "box_caption": "bottle 0.006", "scores": {"class_score": 0.005924224853515625}, "domain": "pixel"}, {"position": {"minX": 116.875, "minY": -34.625, "maxX": 341.5, "maxY": 407.0}, "class_id": 1, "box_caption": "chair 0.006", "scores": {"class_score": 0.00591278076171875}, "domain": "pixel"}, {"position": {"minX": 586.0, "minY": 541.5, "maxX": 659.0, "maxY": 659.5}, "class_id": 0, "box_caption": "bottle 0.006", "scores": {"class_score": 0.005710601806640625}, "domain": "pixel"}, {"position": {"minX": 75.0, "minY": 116.125, "maxX": 363.75, "maxY": 373.0}, "class_id": 2, "box_caption": "stool 0.005", "scores": {"class_score": 0.005275726318359375}, "domain": "pixel"}, {"position": {"minX": 75.375, "minY": 116.375, "maxX": 364.5, "maxY": 372.0}, "class_id": 3, "box_caption": "tripod 0.005", "scores": {"class_score": 0.004962921142578125}, "domain": "pixel"}, {"position": {"minX": 334.75, "minY": 45.0, "maxX": 569.5, "maxY": 409.25}, "class_id": 2, "box_caption": "stool 0.004", "scores": {"class_score": 0.004352569580078125}, "domain": "pixel"}, {"position": {"minX": 335.75, "minY": 47.0, "maxX": 570.5, "maxY": 407.5}, "class_id": 3, "box_caption": "tripod 0.004", "scores": {"class_score": 0.0041351318359375}, "domain": "pixel"}, {"position": {"minX": 368.5, "minY": 17.125, "maxX": 608.0, "maxY": 480.0}, "class_id": 1, "box_caption": "chair 0.002", "scores": {"class_score": 0.0022525787353515625}, "domain": "pixel"}, {"position": {"minX": 35.625, "minY": -19.875, "maxX": 300.5, "maxY": 486.5}, "class_id": 1, "box_caption": "chair 0.002", "scores": {"class_score": 0.002170562744140625}, "domain": "pixel"}, {"position": {"minX": 0.109375, "minY": 412.5, "maxX": 22.734375, "maxY": 693.5}, "class_id": 0, "box_caption": "bottle 0.002", "scores": {"class_score": 0.0020046234130859375}, "domain": "pixel"}, {"position": {"minX": 322.5, "minY": -118.0625, "maxX": 561.0, "maxY": 363.75}, "class_id": 1, "box_caption": "chair 0.002", "scores": {"class_score": 0.00197601318359375}, "domain": "pixel"}, {"position": {"minX": 642.5, "minY": 137.25, "maxX": 671.5, "maxY": 518.0}, "class_id": 0, "box_caption": "bottle 0.002", "scores": {"class_score": 0.0018777847290039062}, "domain": "pixel"}, {"position": {"minX": 304.25, "minY": 124.3125, "maxX": 373.75, "maxY": 335.0}, "class_id": 1, "box_caption": "chair 0.002", "scores": {"class_score": 0.0017995834350585938}, "domain": "pixel"}, {"position": {"minX": 57.71875, "minY": 24.125, "maxX": 183.75, "maxY": 445.5}, "class_id": 1, "box_caption": "chair 0.001", "scores": {"class_score": 0.001373291015625}, "domain": "pixel"}, {"position": {"minX": 453.75, "minY": 6.625, "maxX": 582.5, "maxY": 453.0}, "class_id": 1, "box_caption": "chair 0.001", "scores": {"class_score": 0.0011997222900390625}, "domain": "pixel"}, {"position": {"minX": 540.0, "minY": 572.5, "maxX": 664.0, "maxY": 657.5}, "class_id": 1, "box_caption": "chair 0.001", "scores": {"class_score": 0.0011301040649414062}, "domain": "pixel"}], "class_labels": {"0": "bottle", "1": "chair", "2": "stool", "3": "tripod"}}