{"box_data": [{"position": {"minX": 60.0, "minY": 195.125, "maxX": 341.0, "maxY": 636.0}, "class_id": 1, "box_caption": "chair 0.879", "scores": {"class_score": 0.87939453125}, "domain": "pixel"}, {"position": {"minX": 322.0, "minY": 57.0, "maxX": 470.5, "maxY": 424.75}, "class_id": 1, "box_caption": "chair 0.871", "scores": {"class_score": 0.87060546875}, "domain": "pixel"}, {"position": {"minX": 210.75, "minY": 266.0, "maxX": 327.75, "maxY": 512.5}, "class_id": 1, "box_caption": "chair 0.018", "scores": {"class_score": 0.0182037353515625}, "domain": "pixel"}, {"position": {"minX": 638.5, "minY": -8.5625, "maxX": 670.5, "maxY": 198.5}, "class_id": 1, "box_caption": "chair 0.013", "scores": {"class_score": 0.01306915283203125}, "domain": "pixel"}, {"position": {"minX": 563.0, "minY": 520.5, "maxX": 661.0, "maxY": 671.5}, "class_id": 1, "box_caption": "chair 0.009", "scores": {"class_score": 0.00894927978515625}, "domain": "pixel"}, {"position": {"minX": 573.0, "minY": 14.3125, "maxX": 659.0, "maxY": 92.8125}, "class_id": 1, "box_caption": "chair 0.008", "scores": {"class_score": 0.00839996337890625}, "domain": "pixel"}, {"position": {"minX": 323.5, "minY": 57.625, "maxX": 470.5, "maxY": 424.5}, "class_id": 0, "box_caption": "bottle 0.008", "scores": {"class_score": 0.007793426513671875}, "domain": "pixel"}, {"position": {"minX": 616.5, "minY": 21.40625, "maxX": 656.5, "maxY": 98.75}, "class_id": 1, "box_caption": "chair 0.007", "scores": {"class_score": 0.00662994384765625}, "domain": "pixel"}, {"position": {"minX": 61.75, "minY": 195.125, "maxX": 340.0, "maxY": 635.5}, "class_id": 0, "box_caption": "bottle 0.006", "scores": {"class_score": 0.006389617919921875}, "domain": "pixel"}, {"position": {"minX": 323.5, "minY": 57.625, "maxX": 470.5, "maxY": 424.5}, "class_id": 3, "box_caption": "tripod 0.006", "scores": {"class_score": 0.00612640380859375}, "domain": "pixel"}, {"position": {"minX": 61.75, "minY": 195.125, "maxX": 340.0, "maxY": 635.5}, "class_id": 3, "box_caption": "tripod 0.006", "scores": {"class_score": 0.005619049072265625}, "domain": "pixel"}, {"position": {"minX": 87.625, "minY": 65.625, "maxX": 345.0, "maxY": 568.5}, "class_id": 1, "box_caption": "chair 0.005", "scores": {"class_score": 0.0048980712890625}, "domain": "pixel"}, {"position": {"minX": 498.5, "minY": 9.28125, "maxX": 628.5, "maxY": 39.78125}, "class_id": 1, "box_caption": "chair 0.005", "scores": {"class_score": 0.004558563232421875}, "domain": "pixel"}, {"position": {"minX": 323.5, "minY": 57.625, "maxX": 470.5, "maxY": 424.5}, "class_id": 2, "box_caption": "stool 0.005", "scores": {"class_score": 0.004543304443359375}, "domain": "pixel"}, {"position": {"minX": 40.125, "minY": 137.25, "maxX": 266.0, "maxY": 616.0}, "class_id": 1, "box_caption": "chair 0.005", "scores": {"class_score": 0.004512786865234375}, "domain": "pixel"}, {"position": {"minX": 61.75, "minY": 195.125, "maxX": 340.0, "maxY": 635.5}, "class_id": 2, "box_caption": "stool 0.004", "scores": {"class_score": 0.004367828369140625}, "domain": "pixel"}, {"position": {"minX": 448.5, "minY": 251.0, "maxX": 703.5, "maxY": 796.0}, "class_id": 1, "box_caption": "chair 0.004", "scores": {"class_score": 0.003940582275390625}, "domain": "pixel"}, {"position": {"minX": 648.0, "minY": 4.375, "maxX": 671.0, "maxY": 162.75}, "class_id": 1, "box_caption": "chair 0.003", "scores": {"class_score": 0.00299072265625}, "domain": "pixel"}, {"position": {"minX": 193.5, "minY": 109.5, "maxX": 369.0, "maxY": 584.5}, "class_id": 1, "box_caption": "chair 0.002", "scores": {"class_score": 0.0024967193603515625}, "domain": "pixel"}, {"position": {"minX": 647.0, "minY": 177.875, "maxX": 672.0, "maxY": 444.5}, "class_id": 0, "box_caption": "bottle 0.002", "scores": {"class_score": 0.0022907257080078125}, "domain": "pixel"}, {"position": {"minX": 637.0, "minY": -62.75, "maxX": 672.0, "maxY": 274.0}, "class_id": 1, "box_caption": "chair 0.002", "scores": {"class_score": 0.002117156982421875}, "domain": "pixel"}, {"position": {"minX": 637.5, "minY": 3.5, "maxX": 671.5, "maxY": 362.5}, "class_id": 0, "box_caption": "bottle 0.002", "scores": {"class_score": 0.0019741058349609375}, "domain": "pixel"}, {"position": {"minX": 287.25, "minY": 5.75, "maxX": 477.75, "maxY": 491.0}, "class_id": 1, "box_caption": "chair 0.002", "scores": {"class_score": 0.0019550323486328125}, "domain": "pixel"}, {"position": {"minX": 105.5, "minY": 95.625, "maxX": 247.5, "maxY": 535.5}, "class_id": 1, "box_caption": "chair 0.002", "scores": {"class_score": 0.0019073486328125}, "domain": "pixel"}, {"position": {"minX": 243.75, "minY": 113.875, "maxX": 372.75, "maxY": 482.0}, "class_id": 1, "box_caption": "chair 0.002", "scores": {"class_score": 0.0015954971313476562}, "domain": "pixel"}, {"position": {"minX": 578.5, "minY": 586.0, "maxX": 656.5, "maxY": 668.0}, "class_id": 1, "box_caption": "chair 0.002", "scores": {"class_score": 0.0015048980712890625}, "domain": "pixel"}, {"position": {"minX": 0.109375, "minY": -23.0, "maxX": 23.296875, "maxY": 299.5}, "class_id": 0, "box_caption": "bottle 0.001", "scores": {"class_score": 0.0012903213500976562}, "domain": "pixel"}, {"position": {"minX": 597.0, "minY": 546.5, "maxX": 663.0, "maxY": 675.5}, "class_id": 1, "box_caption": "chair 0.001", "scores": {"class_score": 0.0010385513305664062}, "domain": "pixel"}], "class_labels": {"0": "bottle", "1": "chair", "2": "stool", "3": "tripod"}}